LICENSE.txt
MANIFEST.in
README.rst
setup.py
js/__init__.py
js.flat_ui.egg-info/PKG-INFO
js.flat_ui.egg-info/SOURCES.txt
js.flat_ui.egg-info/dependency_links.txt
js.flat_ui.egg-info/entry_points.txt
js.flat_ui.egg-info/namespace_packages.txt
js.flat_ui.egg-info/not-zip-safe
js.flat_ui.egg-info/requires.txt
js.flat_ui.egg-info/top_level.txt
js/flat_ui/__init__.py
js/flat_ui/test_flat_ui.txt
js/flat_ui/resources/css/flat-ui.css
js/flat_ui/resources/css/flat-ui.min.css
js/flat_ui/resources/fonts/Flat-UI-Icons-16.woff
js/flat_ui/resources/fonts/Flat-UI-Icons-24.woff
js/flat_ui/resources/images/checkbox-2x.png
js/flat_ui/resources/images/checkbox.png
js/flat_ui/resources/images/radio-2x.png
js/flat_ui/resources/images/radio.png
js/flat_ui/resources/images/illustrations/bag.png
js/flat_ui/resources/images/illustrations/book.png
js/flat_ui/resources/images/illustrations/calendar.png
js/flat_ui/resources/images/illustrations/clipboard.png
js/flat_ui/resources/images/illustrations/colors.png
js/flat_ui/resources/images/illustrations/compass.png
js/flat_ui/resources/images/illustrations/gift.png
js/flat_ui/resources/images/illustrations/infinity.png
js/flat_ui/resources/images/illustrations/mail.png
js/flat_ui/resources/images/illustrations/map.png
js/flat_ui/resources/images/illustrations/paper.png
js/flat_ui/resources/images/illustrations/retina.png
js/flat_ui/resources/images/illustrations/share.png
js/flat_ui/resources/images/illustrations/time.png
js/flat_ui/resources/images/pager/next.png
js/flat_ui/resources/images/pager/previous.png
js/flat_ui/resources/images/select/toggle.png
js/flat_ui/resources/images/tile/ribbon-2x.png
js/flat_ui/resources/images/tile/ribbon.png
js/flat_ui/resources/images/todo/done-2x.png
js/flat_ui/resources/images/todo/done.png
js/flat_ui/resources/images/todo/search-2x.png
js/flat_ui/resources/images/todo/search.png
js/flat_ui/resources/images/todo/todo-2x.png
js/flat_ui/resources/images/todo/todo.png
js/flat_ui/resources/images/toggle/block-off.png
js/flat_ui/resources/images/toggle/block-on.png
js/flat_ui/resources/images/toggle/icon-off-2x.png
js/flat_ui/resources/images/toggle/icon-off.png
js/flat_ui/resources/images/toggle/icon-on-2x.png
js/flat_ui/resources/images/toggle/icon-on.png
