Metadata-Version: 1.0
Name: js.flat-ui
Version: 1.1
Summary: Fanstatic packaging of Flat-UI
Home-page: UNKNOWN
Author: UNKNOWN
Author-email: UNKNOWN
License: CC BY 3.0
Platform: UNKNOWN
Classifier: Programming Language :: Python :: 2.6
Classifier: Programming Language :: Python :: 2.7
Classifier: Programming Language :: Python :: 3.2
Classifier: Programming Language :: Python :: Implementation :: PyPy
